calcaraj/__init__.py
calcaraj/basicCalc.py
calcaraj-0.1.0.dist-info/METADATA
calcaraj-0.1.0.dist-info/WHEEL
calcaraj-0.1.0.dist-info/top_level.txt
calcaraj-0.1.0.dist-info/RECORD
