Metadata-Version: 2.1
Name: calcaraj
Version: 0.1.0
Summary: My first Python library!!
Author: Aryan Raj
